README.md
setup.py
extipy/__init__.py
extipy.egg-info/PKG-INFO
extipy.egg-info/SOURCES.txt
extipy.egg-info/dependency_links.txt
extipy.egg-info/not-zip-safe
extipy.egg-info/top_level.txt