Metadata-Version: 1.0
Name: extipy
Version: 0.1
Summary: Kernel manager for connecting to IPython kernels started outside of Jupyter
Home-page: http://github.com/ebanner/extipy
Author: Edward Banner
Author-email: edward.banner@gmail.com
License: MIT
Platform: UNKNOWN
